modbus2mqtt/__init__.py
modbus2mqtt/__main__.py
modbus2mqtt/addToHomeAssistant.py
modbus2mqtt/dataTypes.py
modbus2mqtt/modbus2mqtt.py
modbus2mqtt-0.73.dist-info/LICENSE
modbus2mqtt-0.73.dist-info/METADATA
modbus2mqtt-0.73.dist-info/WHEEL
modbus2mqtt-0.73.dist-info/entry_points.txt
modbus2mqtt-0.73.dist-info/top_level.txt
modbus2mqtt-0.73.dist-info/RECORD
