Metadata-Version: 2.2
Name: modbus2mqtt
Version: 0.73
Summary: Bridge from Modbus to MQTT
Home-page: https://github.com/mbs38/spicierModbus2mqtt
Author: Max Brüggemann
Author-email: mail@maxbrueggemann.de
License-File: LICENSE
Requires-Dist: paho-mqtt
Requires-Dist: pymodbus
Requires-Dist: serial
Dynamic: author
Dynamic: author-email
Dynamic: home-page
Dynamic: requires-dist
Dynamic: summary
